biseau/__init__.py
biseau/__main__.py
biseau/asp_to_dot.py
biseau/core.py
biseau/dot_writer.py
biseau/export.py
biseau/format_converters.py
biseau/module_loader.py
biseau/run_on_types.py
biseau/script.py
biseau/utils.py
biseau-0.0.20.dist-info/METADATA
biseau-0.0.20.dist-info/WHEEL
biseau-0.0.20.dist-info/top_level.txt
biseau-0.0.20.dist-info/RECORD
