Metadata-Version: 2.1
Name: biseau
Version: 0.0.20
Summary: Draw graphs using Answer Set Programming
Home-page: https://gitlab.inria.fr/lbourneu/biseau
Author: Lucas Bourneuf
Author-email: lucas.bourneuf@inria.fr
License: GPL
Keywords: Answer Set Programming,wrapper,clingo
Platform: UNKNOWN
Classifier: Development Status :: 4 - Beta
Classifier: Intended Audience :: Science/Research
Classifier: Programming Language :: Python :: 3
Classifier: Programming Language :: Python :: 3.5
Classifier: Programming Language :: ASP
Requires-Dist: Pillow (>=6.2.1)
Requires-Dist: clyngor (>=0.3.24)
Requires-Dist: pydot (>=1.2.4)
Requires-Dist: pytest (>=3.9.2)
